trac/rt/__init__.py
trac/rt/_version.py
trac/rt/exceptions.py
trac/rt/api/__init__.py
trac/rt/api/core_api.py
trac/rt/api/define_func.py
trac/rt/config/__init__.py
trac/rt/config/config.py
trac/rt/exec/__init__.py
trac/rt/exec/actors.py
trac/rt/exec/context.py
trac/rt/exec/dev_mode.py
trac/rt/exec/engine.py
trac/rt/exec/functions.py
trac/rt/exec/graph.py
trac/rt/exec/graph_builder.py
trac/rt/exec/runtime.py
trac/rt/impl/__init__.py
trac/rt/impl/config_parser.py
trac/rt/impl/data.py
trac/rt/impl/repositories.py
trac/rt/impl/storage.py
trac/rt/impl/util.py
trac/rt/launch/__init__.py
trac/rt/launch/launch.py
trac/rt/metadata/__init__.py
trac/rt/metadata/custom.py
trac/rt/metadata/data.py
trac/rt/metadata/file.py
trac/rt/metadata/flow.py
trac/rt/metadata/job.py
trac/rt/metadata/model.py
trac/rt/metadata/object.py
trac/rt/metadata/object_id.py
trac/rt/metadata/search.py
trac/rt/metadata/stoarge.py
trac/rt/metadata/tag.py
trac/rt/metadata/type.py
trac_runtime-0.3.1.dist-info/LICENSE
trac_runtime-0.3.1.dist-info/METADATA
trac_runtime-0.3.1.dist-info/WHEEL
trac_runtime-0.3.1.dist-info/top_level.txt
trac_runtime-0.3.1.dist-info/RECORD
