Metadata-Version: 2.1
Name: trac-runtime
Version: 0.3.1
Summary: TRAC Model Runtime for Python
Home-page: https://github.com/accenture/trac
Author: Martin Traverse
Author-email: martin.traverse@accenture.com
License: Apache-2.0
Project-URL: Documentation, https://trac-platform.readthedocs.io/
Project-URL: Bug Tracker, https://github.com/accenture/trac/issues
Platform: any
Classifier: Programming Language :: Python :: 3
Classifier: License :: OSI Approved :: Apache Software License
Classifier: Operating System :: OS Independent
Requires-Python: >=3.7
License-File: LICENSE
Requires-Dist: pandas (<2.0.0,>=1.0.0)
Requires-Dist: pyspark (<3.3.0,>=2.4.0)
Requires-Dist: pyyaml (<6.0.0,>=5.3.0)
